pta/__init__.py
pta/commons.py
pta/compartment_parameters.py
pta/concentrations_prior.py
pta/constants.py
pta/distributions.py
pta/flux_space.py
pta/metabolite.py
pta/metabolite_interpreter.py
pta/model_assessment.py
pta/pmo.py
pta/thermodynamic_space.py
pta/utils.py
pta/data/__init__.py
pta/data/compartment_parameters/__init__.py
pta/data/compartment_parameters/default.csv
pta/data/compartment_parameters/e_coli.csv
pta/data/compartment_parameters/human.csv
pta/data/concentration_priors/M9_aerobic.csv
pta/data/concentration_priors/M9_anaerobic.csv
pta/data/concentration_priors/__init__.py
pta/data/concentration_priors/ecoli_M9_ac.csv
pta/data/concentration_priors/ecoli_M9_fru.csv
pta/data/concentration_priors/ecoli_M9_gal.csv
pta/data/concentration_priors/ecoli_M9_glc.csv
pta/data/concentration_priors/ecoli_M9_glcn.csv
pta/data/concentration_priors/ecoli_M9_glyc.csv
pta/data/concentration_priors/ecoli_M9_pyr.csv
pta/data/concentration_priors/ecoli_M9_specific.csv
pta/data/concentration_priors/ecoli_M9_succ.csv
pta/data/concentration_priors/ecoli_M9_unspecific.csv
pta/data/models/__init__.py
pta/data/models/e_coli_core.xml
pta/data/models/iJO1366.xml
pta/gibbs_estimators/__init__.py
pta/gibbs_estimators/equilibrator_gibbs_estimator.py
pta/gibbs_estimators/gibbs_estimator_interface.py
pta-0.1.0.dist-info/METADATA
pta-0.1.0.dist-info/WHEEL
pta-0.1.0.dist-info/top_level.txt
pta-0.1.0.dist-info/zip-safe
pta-0.1.0.dist-info/RECORD
