Metadata-Version: 2.1
Name: pta
Version: 0.1.0
Summary: Probabilistic Thermodynamic Analysis of metabolic networks.
Home-page: https://gitlab.com/csb.ethz/pta
Author: Mattia G. Gollub
Author-email: mattia.gollub@bsse.ethz.ch
License: GPLv3 License
Download-URL: https://pypi.org/project/pta
Project-URL: Source Code, https://gitlab.com/csb.ethz/pta
Project-URL: Documentation, https://probabilistic-thermodynamic-analysis.readthedocs.io/en/latest/
Project-URL: Bug Tracker, https://gitlab.com/csb.ethz/pta/issues
Keywords: Gibbs energy,eQuilibrator,thermodynamics,metabolic network,reaction network,sampling
Platform: UNKNOWN
Classifier: Development Status :: 1 - Planning
Classifier: Intended Audience :: Science/Research
Classifier: Topic :: Scientific/Engineering :: Bio-Informatics
Classifier: License :: OSI Approved :: GNU General Public License v3 (GPLv3)
Classifier: Natural Language :: English
Classifier: Programming Language :: Python :: 3.8
Requires-Python: >=3.8
Requires-Dist: equilibrator-api (==0.4.0b5)
Requires-Dist: cvxpy (>=1.1.1)
Requires-Dist: efmtool (>=0.1.5)
